py24/__init__.py
py24-1.1.1.dist-info/licenses/LICENSE
py24-1.1.1.dist-info/METADATA
py24-1.1.1.dist-info/WHEEL
py24-1.1.1.dist-info/top_level.txt
py24-1.1.1.dist-info/RECORD
