Metadata-Version: 2.4
Name: Py24
Version: 1.1.1
Summary: A simple python package to interface with Pi24 installations.
Author-email: Lordseriouspig <lordseriouspig@gmail.com>
License-Expression: MIT
Project-URL: Homepage, https://github.com/lordseriouspig/pi24-monitor
Project-URL: Issues, https://github.com/lordseriouspig/pi24-monitor/issues
Classifier: Programming Language :: Python :: 3
Classifier: Operating System :: OS Independent
Requires-Python: >=3.9
License-File: LICENSE
Dynamic: license-file
